README.md
setup.py
Topsis_Kanika_102017074.egg-info/PKG-INFO
Topsis_Kanika_102017074.egg-info/SOURCES.txt
Topsis_Kanika_102017074.egg-info/dependency_links.txt
Topsis_Kanika_102017074.egg-info/requires.txt
Topsis_Kanika_102017074.egg-info/top_level.txt
topsis/__init__.py
topsis/topsis.py