Metadata-Version: 2.1
Name: Topsis-Kanika-102017074
Version: 1.0
Summary: Python implementation of the Technique for Order of Preference by Similarity to Ideal Solution (TOPSIS)
Author: Kanika
